hdl/types.svh
`ifndef TYPES_SVH
`define TYPES_SVH

typedef struct packed {
  logic [10:0] rect_x;
  logic [9:0] rect_y;
  logic [10:0] rect_w;
  logic [9:0] rect_h;
  logic [10:0] saber_x;
  logic [9:0] saber_y;
} location_t;

typedef struct packed {
  logic [2:0] health;
  location_t location;
  logic [1:0] saber_state;
  logic [10:0] saber_attack_x;
  logic [9:0] saber_attack_y;
} data_t;

`endif // TYPES_SVH

hdl/spi_rx.sv
`timescale 1ns / 1ps
`default_nettype none // prevents system from inferring an undeclared logic (good practice)
module spi_rx
       #(  parameter DATA_WIDTH = 8
        )
        ( input wire clk_in,
          input wire rst_in,
          input wire data_in,
          input wire data_clk_in,
          input wire sel_in,
          output logic [DATA_WIDTH-1:0] data_out,
          output logic new_data_out
        );
  logic [$clog2(DATA_WIDTH)-1:0] ch = DATA_WIDTH-1;
  logic prev;

  always_ff @(posedge clk_in) begin
	  if (rst_in) begin
		  ch <= DATA_WIDTH-1;
		  new_data_out <= 0;
    end else begin
		  if (sel_in == 0) begin
			  if (prev == 0 && data_clk_in == 1) begin
				  data_out[ch] <= data_in;
			  
          if (ch == 0) begin
            new_data_out <= 1;
            ch <= DATA_WIDTH-1;
          end else begin
            ch <= ch - 1;
            new_data_out <= 0;
		      end
        end
		  end else begin
			  new_data_out <= 0;
		  end
		  prev <= data_clk_in;
	  end
  end
endmodule

`default_nettype wire // prevents system from inferring an undeclared logic (good practice)

hdl/syncer.sv
`timescale 1ns / 1ps
`default_nettype none
`include "hdl/types.svh"

module syncer(
    input wire clk_pixel_in,
    input wire rst_in,
    input location_t location_in,
    input wire location_in_valid,
    input wire data_in,
    input wire data_clk_in,
    input wire sel_in,
    output location_t player_location_out,
    output data_t opponent_data_out,
    output logic data_out_valid
  );

  logic player_location_received;
  logic opponent_data_received;
  location_t player_location;
  data_t opponent_data;
  logic opponent_data_valid;

  spi_rx #(
    .DATA_WIDTH($bits(data_t))
  ) spi_rx_inst ( 
    .clk_in(clk_pixel_in),
    .rst_in(rst_in),
    .data_in(data_in),
    .data_clk_in(data_clk_in),
    .sel_in(sel_in),
    .data_out(opponent_data),
    .new_data_out(opponent_data_valid)
  );

  always_ff @(posedge clk_pixel_in) begin
    if (rst_in) begin
      player_location_received <= 0;
      opponent_data_received <= 0;
      player_location <= 0;
      data_out_valid <= 0;
    end else begin
      if (player_location_received && opponent_data_received) begin
        data_out_valid <= 1'b1;
        player_location_out <= player_location;
        opponent_data_out <= opponent_data;
        player_location_received <= 0;
        opponent_data_received <= 0;
      end else if (player_location_received) begin
        if (opponent_data_valid) begin
          opponent_data_received <= 1'b1;
        end
        data_out_valid <= 0;
      end else begin
        if (opponent_data_valid) begin
          opponent_data_received <= 1'b1;
        end
        if (location_in_valid) begin
          player_location_received <= 1'b1;
          player_location <= location_in;
        end
        data_out_valid <= 0;
      end
    end
  end
  
endmodule

`default_nettype wire

sim/syncer_tb.sv
`timescale 1ns / 1ps
`default_nettype none
`include "hdl/types.svh"

module syncer_tb();
  localparam DATA_WIDTH = $bits(data_t);

  logic clk_in;
  logic rst_in;

  logic [88:0] data_to_send;

  // inputs from outside
  logic data_in, data_clk_in, sel_in;

  // inputs from same fpga
  location_t player_location;
  logic player_location_valid;

  // outputs to print
  location_t syncer_player_location;
  data_t opponent_data;
  logic syncer_data_valid;

  // SPI_RX.
  syncer syncer_inst(
    .clk_pixel_in(clk_in),
    .rst_in(rst_in),
    .location_in(player_location),
    .location_in_valid(player_location_valid),
    .data_in(data_in),
    .data_clk_in(data_clk_in),
    .sel_in(sel_in),
    .player_location_out(syncer_player_location),
    .opponent_data_out(opponent_data),
    .data_out_valid(syncer_data_valid)
  );

  always begin
      #5;  //every 5 ns switch...so period of clock is 10 ns...100 MHz clock
      clk_in = !clk_in;
  end
  //initial block...this is our test simulation
  initial begin
    $dumpfile("syncer.vcd"); //file to store value change dump (vcd)
    $dumpvars(0, syncer_tb);
    $display("Starting Sim"); //print nice message at start
    clk_in = 0;
    rst_in = 0;
    sel_in = 1;
    #10;
    rst_in = 1;
    #10;
    rst_in = 0;
    #10;
    sel_in = 0;
    player_location_valid = 0;
    data_to_send = 89'b101_00000100001_1010101010_11111011111_0101010101_10101010101_0101010101_00_10101010101_0101010101;
    for (int i = 0; i < $bits(data_t); i=i+1) begin
      data_clk_in = 0;
      data_in = data_to_send[$bits(data_t)-1-i];
      #500;
      if (i == 15) begin
        data_clk_in = 1;
        #230;
        player_location_valid = 1'b1;
        player_location = 63'b11100100001_1111111010_11100011111_0101011101_10101010101_0101010101;
        #10;
        player_location_valid = 0;
        #260;
      end else begin
        data_clk_in = 1;
        #500;
      end
    end
    sel_in = 1;

    #100;

    #10;
    rst_in = 1;
    #10;
    rst_in = 0;
    #10;
    player_location_valid = 1'b1;
    player_location = 63'b00000100001_1111111010_11100011111_0101011101_10101010101_0101010101;
    #10;
    sel_in = 0;
    player_location_valid = 0;
    data_to_send = 89'b101_00011101101_1010101010_11111011111_0101010101_10101010101_0101010101_00_10101010101_0101010101;
    for (int i = 0; i < $bits(data_t); i=i+1) begin
      data_clk_in = 0;
      data_in = data_to_send[$bits(data_t)-1-i];
      #500;
      data_clk_in = 1;
      #500;
    end
    sel_in = 1;

    #100;

    #10;
    rst_in = 1;
    #10;
    rst_in = 0;
    #10;
    sel_in = 0;
    player_location_valid = 0;
    data_to_send = 89'b101_00000100001_1010101010_11111011011_0111011101_10101010101_0101010101_00_10101010101_0101010101;
    for (int i = 0; i < $bits(data_t); i=i+1) begin
      data_clk_in = 0;
      data_in = data_to_send[$bits(data_t)-1-i];
      #500;
      data_clk_in = 1;
      #500;
    end
    sel_in = 1;
    #10;
    player_location_valid = 1'b1;
    player_location = 63'b01010101011_1111111010_11100011111_0101011101_10101010101_0101010101;

    #100;

    $display("Finishing Sim"); //print nice message at end
    $finish;
  end
endmodule
`default_nettype wire

syncer.vcd
$date
	Wed Nov 29 18:14:27 2023
$end
$version
	Icarus Verilog
$end
$timescale
	1ps
$end
$scope module syncer_tb $end
$var wire 63 ! syncer_player_location [62:0] $end
$var wire 1 " syncer_data_valid $end
$var wire 89 # opponent_data [88:0] $end
$var parameter 32 $ DATA_WIDTH $end
$var reg 1 % clk_in $end
$var reg 1 & data_clk_in $end
$var reg 1 ' data_in $end
$var reg 89 ( data_to_send [88:0] $end
$var reg 63 ) player_location [62:0] $end
$var reg 1 * player_location_valid $end
$var reg 1 + rst_in $end
$var reg 1 , sel_in $end
$scope module syncer_inst $end
$var wire 1 % clk_pixel_in $end
$var wire 1 & data_clk_in $end
$var wire 1 ' data_in $end
$var wire 63 - location_in [62:0] $end
$var wire 1 * location_in_valid $end
$var wire 1 + rst_in $end
$var wire 1 , sel_in $end
$var wire 1 . opponent_data_valid $end
$var wire 89 / opponent_data [88:0] $end
$var reg 1 " data_out_valid $end
$var reg 89 0 opponent_data_out [88:0] $end
$var reg 1 1 opponent_data_received $end
$var reg 63 2 player_location [62:0] $end
$var reg 63 3 player_location_out [62:0] $end
$var reg 1 4 player_location_received $end
$scope module spi_rx_inst $end
$var wire 1 % clk_in $end
$var wire 1 & data_clk_in $end
$var wire 1 ' data_in $end
$var wire 1 + rst_in $end
$var wire 1 , sel_in $end
$var parameter 32 5 DATA_WIDTH $end
$var reg 7 6 ch [6:0] $end
$var reg 89 7 data_out [88:0] $end
$var reg 1 . new_data_out $end
$var reg 1 8 prev $end
$upscope $end
$upscope $end
$scope begin $ivl_for_loop0 $end
$var integer 32 9 i [31:0] $end
$upscope $end
$scope begin $ivl_for_loop1 $end
$var integer 32 : i [31:0] $end
$upscope $end
$scope begin $ivl_for_loop2 $end
$var integer 32 ; i [31:0] $end
$upscope $end
$upscope $end
$enddefinitions $end
$comment Show the parameter values. $end
$dumpall
b1011001 5
b1011001 $
$end
#0
$dumpvars
b0 ;
b0 :
b0 9
x8
bx 7
b1011000 6
x4
bx 3
bx 2
x1
bx 0
bx /
x.
bx -
1,
0+
x*
bx )
bx (
x'
x&
0%
bx #
x"
bx !
$end
#5000
0.
0"
1%
#10000
0%
1+
#15000
b0 2
01
04
1%
#20000
0%
0+
#25000
1%
#30000
0%
1'
0&
b10100000100001101010101011111011111010101010110101010101010101010100101010101010101010101 (
0*
0,
#35000
08
1%
#40000
0%
#45000
1%
#50000
0%
#55000
1%
#60000
0%
#65000
1%
#70000
0%
#75000
1%
#80000
0%
#85000
1%
#90000
0%
#95000
1%
#100000
0%
#105000
1%
#110000
0%
#115000
1%
#120000
0%
#125000
1%
#130000
0%
#135000
1%
#140000
0%
#145000
1%
#150000
0%
#155000
1%
#160000
0%
#165000
1%
#170000
0%
#175000
1%
#180000
0%
#185000
1%
#190000
0%
#195000
1%
#200000
0%
#205000
1%
#210000
0%
#215000
1%
#220000
0%
#225000
1%
#230000
0%
#235000
1%
#240000
0%
#245000
1%
#250000
0%
#255000
1%
#260000
0%
#265000
1%
#270000
0%
#275000
1%
#280000
0%
#285000
1%
#290000
0%
#295000
1%
#300000
0%
#305000
1%
#310000
0%
#315000
1%
#320000
0%
#325000
1%
#330000
0%
#335000
1%
#340000
0%
#345000
1%
#350000
0%
#355000
1%
#360000
0%
#365000
1%
#370000
0%
#375000
1%
#380000
0%
#385000
1%
#390000
0%
#395000
1%
#400000
0%
#405000
1%
#410000
0%
#415000
1%
#420000
0%
#425000
1%
#430000
0%
#435000
1%
#440000
0%
#445000
1%
#450000
0%
#455000
1%
#460000
0%
#465000
1%
#470000
0%
#475000
1%
#480000
0%
#485000
1%
#490000
0%
#495000
1%
#500000
0%
#505000
1%
#510000
0%
#515000
1%
#520000
0%
#525000
1%
#530000
0%
1&
#535000
18
b1010111 6
b1xxxxxxxxxxxxxxxxxxxxxxxxxxxxxxxxxxxxxxxxxxxxxxxxxxxxxxxxxxxxxxxxxxxxxxxxxxxxxxxxxxxxxxxx /
b1xxxxxxxxxxxxxxxxxxxxxxxxxxxxxxxxxxxxxxxxxxxxxxxxxxxxxxxxxxxxxxxxxxxxxxxxxxxxxxxxxxxxxxxx 7
1%
